{"status_code": 200, "dominant_lang": null, "url": "http://0120410465.com/", "head": {"title": "\u008a\u0094\u008e\u00ae\u0089\u00ef\u008e\u00d0\u0083W\u0083\u0085\u0083l\u0083\u008a\u0083J\u0081@\u0083X\u0083^\u0083b\u0083t\u0083y\u0081[\u0083W", "script": [], "script_count": 0, "link": [], "link_count": 0, "favicon": null, "meta": [{"name": null, "content": "text/html; charset=Shift_JIS"}, {"name": "ROBOTS", "content": null}, {"name": "description", "content": "junerika.inc"}, {"name": "keywords", "content": "\u008eD\u0096y\u008es\u0081A\u0096k\u008aC\u0093\u00b9\u0081A\u0089\u00ee\u008c\u00ec\u0095\u00db\u008c\u00af,\u0093\u008c\u008b\u00e6,\u0097v\u008ex\u0089\u0087,\u0092n\u0088\u00e6\u0095\u00ef\u008a\u0087\u008ex\u0089\u0087\u0083Z\u0083\u0093\u0083^\u0081[,\u0096k\u008b\u00e6,\u0088\u00e3\u0097\u00c3,\u0083W\u0083\u0085\u0083l\u0083\u008a\u0083J,junerika,\u0082\u00b6\u0082\u00e3\u0082\u00cb\u0082\u00e8\u0082\u00a9,\u0083f\u0083C\u0083T\u0081[\u0083r\u0083X,\u0089\u00ee\u008c\u00ec\u0097\\\u0096h,\u0089\u00ee\u008c\u00ec\u008e{\u0090\u00dd,\u0092\u00ca\u008f\u008a\u0089\u00ee\u008c\u00ec,\u0083C\u0081[\u0083\u0089\u0083C\u0083t,\u0083t\u0083B\u0083b\u0083g\u0083l\u0083X,\u0089\u00ee\u008c\u00ec\u0097\\\u0096h\u0083Z\u0083\u0093\u0083^\u0081[,elife,\u008d\u0082\u0097\u00ee\u008e\u00d2,\u0096k\u008aC\u0093\u00b9,\u008eD\u0096y\u008es,\u0091\u0081\u0088\u00ee\u0093c,\u0093\u008c\u008b\u00e6,\u0083I\u0083]\u0083\u0093,\u0083G\u0083\u008b\u0083_\u0083\u008a\u0081[\u0083w\u0083\u008b\u0083X,\u008a\u00c2\u008b\u00ab,\u008c\u0092\u008dN"}, {"name": "META HTTP-EQUIV=", "content": "text/html;charset=x-sjis"}, {"name": null, "content": "0;URL=http://www.kaigo-yobou.com/file/202206.pdf"}, {"name": "GENERATOR", "content": "JustSystems Homepage Builder Version 18.0.14.0 for Windows"}, {"name": null, "content": "text/css"}], "meta_count": 8}, "text": {"original": {"h1": null, "h2": null, "h3": null, "h4": null, "h5": null, "strong": null, "p": null, "mark": null}, "english": {"h1": null, "h2": null, "h3": null, "h4": null, "h5": null, "strong": null, "p": null, "mark": null}}, "body": {"a": [], "img": [], "img_biggest": {"src": null, "size": [0, 0], "alt": null, "byte": null, "ocr": null}, "img_smallest": {"src": null, "size": [0, 0], "alt": null, "byte": null, "ocr": null}, "audio": []}}